vois/__init__.py
vois/colors.py
vois/cssUtils.py
vois/download.py
vois/eucountries.py
vois/geojsonUtils.py
vois/interMap.py
vois/ipytrees.py
vois/leafletMap.py
vois/svgBarChart.py
vois/svgBubblesChart.py
vois/svgGraph.py
vois/svgHeatmap.py
vois/svgMap.py
vois/svgPackedCirclesChart.py
vois/svgRankChart.py
vois/svgUtils.py
vois/textpopup.py
vois/treemapPlotly.py
vois/urlOpen.py
vois/urlUpdate.py
vois/geo/Map.py
vois/geo/__init__.py
vois/geo/mapUtils.py
vois/geo/bdap/__init__.py
vois/geo/bdap/rasterAPI.py
vois/geo/bdap/rasterlayer.py
vois/geo/bdap/vectorlayer.py
vois/templates/Content.py
vois/templates/Image.py
vois/templates/MainConfigurator.py
vois/templates/PageConfigurator.py
vois/templates/PlotlyChart.py
vois/templates/SVGdrawing.py
vois/templates/__init__.py
vois/templates/dynamicButton.py
vois/templates/template1panel.py
vois/templates/template2panels.py
vois/templates/template3panels.py
vois/vuetify/Button.py
vois/vuetify/ColorPicker.py
vois/vuetify/DatePicker.py
vois/vuetify/DayCalendar.py
vois/vuetify/IconClipboard.py
vois/vuetify/Label.py
vois/vuetify/MultiSwitch.py
vois/vuetify/Progress.py
vois/vuetify/Radio.py
vois/vuetify/RangeSlider.py
vois/vuetify/Slider.py
vois/vuetify/SliderFloat.py
vois/vuetify/Switch.py
vois/vuetify/Tabs.py
vois/vuetify/TextList.py
vois/vuetify/Toggle.py
vois/vuetify/UploadImage.py
vois/vuetify/UploadJson.py
vois/vuetify/__init__.py
vois/vuetify/app.py
vois/vuetify/basemaps.py
vois/vuetify/card.py
vois/vuetify/cardsGrid.py
vois/vuetify/datatable.py
vois/vuetify/dialogGeneric.py
vois/vuetify/dialogMessage.py
vois/vuetify/dialogWait.py
vois/vuetify/dialogYesNo.py
vois/vuetify/fab.py
vois/vuetify/fontsettings.py
vois/vuetify/footer.py
vois/vuetify/iconButton.py
vois/vuetify/layers.py
vois/vuetify/mainPage.py
vois/vuetify/menu.py
vois/vuetify/page.py
vois/vuetify/paletteEditor.py
vois/vuetify/palettePicker.py
vois/vuetify/palettePickerEx.py
vois/vuetify/popup.py
vois/vuetify/prova.py
vois/vuetify/queryStrings.py
vois-1.0.40.dist-info/licenses/LICENCE
vois-1.0.40.dist-info/METADATA
vois-1.0.40.dist-info/WHEEL
vois-1.0.40.dist-info/top_level.txt
vois-1.0.40.dist-info/RECORD
