Metadata-Version: 2.4
Name: vois
Version: 1.0.40
Summary: A Python Voilà simplification library
Author-email: Davide De Marchi <davide.de-marchi@ec.europa.eu>
Maintainer-email: Davide De Marchi <davide.de-marchi@ec.europa.eu>
License-Expression: EUPL-1.2
Project-URL: homepage, https://github.com/DavideDeMarchi/vois
Project-URL: Bug Reports, https://github.com/DavideDeMarchi/vois/issues
Project-URL: documentation, https://vois.readthedocs.io/en/latest/
Project-URL: Source, https://github.com/DavideDeMarchi/vois/
Project-URL: repository, https://github.com/DavideDeMarchi/vois/
Keywords: Voilà,dashboards,setuptools,development
Classifier: Development Status :: 4 - Beta
Classifier: Intended Audience :: Developers
Classifier: Topic :: Software Development :: Build Tools
Classifier: Programming Language :: Python :: 3
Classifier: Programming Language :: Python :: 3.9
Classifier: Programming Language :: Python :: 3.10
Classifier: Programming Language :: Python :: 3.11
Classifier: Programming Language :: Python :: 3.12
Classifier: Programming Language :: Python :: 3 :: Only
Requires-Python: >=3.9
License-File: LICENCE
Requires-Dist: Pillow>=9.4.0
Requires-Dist: traitlets>=5.9.0
Requires-Dist: ipywidgets>=7.7.0
Requires-Dist: requests>=2.28.0
Requires-Dist: ipykernel
Requires-Dist: pandas
Requires-Dist: ipyvuetify
Requires-Dist: ipytree
Requires-Dist: ipyevents
Requires-Dist: plotly
Requires-Dist: ipyleaflet
Dynamic: license-file
